{
  "main": {
    "id": "de782b340cd47fed",
    "type": "split",
    "children": [
      {
        "id": "aa78cb16f2acd927",
        "type": "tabs",
        "children": [
          {
            "id": "733a9e8bcf4b845e",
            "type": "leaf",
            "state": {
              "type": "markdown",
              "state": {
                "file": "Programming Hub/Languages/Javascript/0. Vanilla JS/5. Behind the Scenes/Mind map.md",
                "mode": "preview",
                "source": false
              }
            }
          },
          {
            "id": "8d33ced0f020daf0",
            "type": "leaf",
            "state": {
              "type": "markdown",
              "state": {
                "file": "Programming Hub/Languages/Javascript/0. Vanilla JS/5. Behind the Scenes/1. JS Engine & Runtime/3. Javascript Engine.md",
                "mode": "preview",
                "source": false
              }
            }
          },
          {
            "id": "14f958c5adfe35dc",
            "type": "leaf",
            "state": {
              "type": "markdown",
              "state": {
                "file": "Programming Hub/Languages/Javascript/0. Vanilla JS/5. Behind the Scenes/1. JS Engine & Runtime/1. Compilation vs Interpretation vs Just-in-Time.md",
                "mode": "preview",
                "source": false
              }
            }
          },
          {
            "id": "43becf715ccf2ac2",
            "type": "leaf",
            "state": {
              "type": "markdown",
              "state": {
                "file": "Programming Hub/Languages/Javascript/0. Vanilla JS/5. Behind the Scenes/1. JS Engine & Runtime/2. JS Runtime in Browser.md",
                "mode": "preview",
                "source": false
              }
            }
          }
        ]
      }
    ],
    "direction": "vertical"
  },
  "left": {
    "id": "214f32132c1f1168",
    "type": "split",
    "children": [
      {
        "id": "fb560102630d81f2",
        "type": "tabs",
        "children": [
          {
            "id": "115f94c009a0a5d9",
            "type": "leaf",
            "state": {
              "type": "file-explorer",
              "state": {
                "sortOrder": "alphabetical"
              }
            }
          },
          {
            "id": "cda124f4e13b0e0d",
            "type": "leaf",
            "state": {
              "type": "search",
              "state": {
                "query": "",
                "matchingCase": false,
                "explainSearch": false,
                "collapseAll": false,
                "extraContext": false,
                "sortOrder": "alphabetical"
              }
            }
          },
          {
            "id": "4f55e929f2550e85",
            "type": "leaf",
            "state": {
              "type": "bookmarks",
              "state": {}
            }
          },
          {
            "id": "4819e8b65497dc14",
            "type": "leaf",
            "state": {
              "type": "mk-path-view",
              "state": {}
            }
          }
        ]
      }
    ],
    "direction": "horizontal",
    "width": 219.5
  },
  "right": {
    "id": "d3823d2f56e3afac",
    "type": "split",
    "children": [
      {
        "id": "bbdf2e5837fdb3dd",
        "type": "tabs",
        "children": [
          {
            "id": "83cf6139e8f63f11",
            "type": "leaf",
            "state": {
              "type": "backlink",
              "state": {
                "file": "Programming Hub/Languages/Javascript/0. Vanilla JS/5. Behind the Scenes/Mind map.md",
                "collapseAll": false,
                "extraContext": false,
                "sortOrder": "alphabetical",
                "showSearch": false,
                "searchQuery": "",
                "backlinkCollapsed": false,
                "unlinkedCollapsed": false
              }
            }
          },
          {
            "id": "a859666849d26cc5",
            "type": "leaf",
            "state": {
              "type": "outgoing-link",
              "state": {
                "file": "Programming Hub/Languages/Javascript/0. Vanilla JS/5. Behind the Scenes/Mind map.md",
                "linksCollapsed": false,
                "unlinkedCollapsed": true
              }
            }
          },
          {
            "id": "9d4963eb752e117b",
            "type": "leaf",
            "state": {
              "type": "tag",
              "state": {
                "sortOrder": "frequency",
                "useHierarchy": true
              }
            }
          },
          {
            "id": "51ab8748b36ecd1c",
            "type": "leaf",
            "state": {
              "type": "outline",
              "state": {
                "file": "Programming Hub/Languages/Javascript/0. Vanilla JS/5. Behind the Scenes/Mind map.md"
              }
            }
          },
          {
            "id": "592ad7a0a1ebc996",
            "type": "leaf",
            "state": {
              "type": "advanced-tables-toolbar",
              "state": {}
            }
          },
          {
            "id": "07fdbaa6a9bc346a",
            "type": "leaf",
            "state": {
              "type": "empty",
              "state": {}
            }
          },
          {
            "id": "965bceb0fed0291b",
            "type": "leaf",
            "state": {
              "type": "Saved Queries View",
              "state": {}
            }
          }
        ],
        "currentTab": 6
      }
    ],
    "direction": "horizontal",
    "width": 200,
    "collapsed": true
  },
  "left-ribbon": {
    "hiddenItems": {
      "switcher:Open quick switcher": false,
      "graph:Open graph view": false,
      "canvas:Create new canvas": false,
      "daily-notes:Open today's daily note": false,
      "templates:Insert template": false,
      "command-palette:Open command palette": false,
      "obsidian-advanced-slides:Show Slide Preview": false,
      "table-editor-obsidian:Advanced Tables Toolbar": false,
      "obsidian-excalidraw-plugin:Create new drawing": false
    }
  },
  "active": "733a9e8bcf4b845e",
  "lastOpenFiles": [
    "Programming Hub/Languages/Javascript/0. Vanilla JS/5. Behind the Scenes/1. JS Engine & Runtime/3. Javascript Engine.md",
    "Programming Hub/Languages/Javascript/0. Vanilla JS/5. Behind the Scenes/1. JS Engine & Runtime/2. JS Runtime in Browser.md",
    "Programming Hub/Languages/Javascript/0. Vanilla JS/5. Behind the Scenes/1. JS Engine & Runtime/1. Compilation vs Interpretation vs Just-in-Time.md",
    "Programming Hub/Languages/Javascript/0. Vanilla JS/5. Behind the Scenes/Mind map.md",
    "Personal/Homepage/Hello.md",
    "Programming Hub/Languages/Javascript/0. Vanilla JS/1. Fundamentals 1/1. What is JS.md",
    "Programming Hub/Languages/Javascript/0. Vanilla JS/1. Fundamentals 1/0.2 History.md",
    "Programming Hub/Languages/Javascript/0. Vanilla JS/0. Pathways/Pathways.md",
    "Programming Hub/Languages/Javascript/0. Vanilla JS/5. Behind the Scenes/1. JS Engine & Runtime/5. Primitive vs Reference.md",
    "cropped_image.png",
    "Resources/Behind topics.png",
    "Resources/What is js.png",
    "Resources/TDZ.png",
    "Resources/Primitive vs Reference.png",
    "Resources/Primitive vs Ref 2.png",
    "Resources/JS Runtime2.png",
    "Resources/JS runtime.png",
    "Resources/JIT.png",
    "Resources/Hoisting2.png",
    "readme.md",
    "Project Alpha.md",
    "Personal/Homepage/😍 Hello.md",
    "Personal/Homepage/Welcome To My Second Brain.md",
    "Personal/Homepage/Homepage.md",
    "Personal/Homepage/~syncthing~Homepage.md.tmp",
    "Programming Hub/Languages/Javascript/1. Frameworks",
    "Programming Hub/Languages/Javascript/0. Vanilla JS",
    "Personal/Homepage/Untitled.canvas",
    "Home.md",
    "Resources",
    "Untitled.canvas",
    "2024-06-15.md",
    "Tags",
    "Personal/Homepage",
    "Resources/What is Function😍.pdf",
    "Excalidraw/Drawing 2024-06-15 12.09.10.excalidraw.md",
    "Programming Hub/Languages/C++/1. Fundamentals/3. Function/What is Function.md",
    "Programming Hub/Languages/Javascript/0. Vanilla JS/6. Function Deep",
    "Programming Hub/Languages/Javascript/0. Vanilla JS/5. Behind the Scenes/1. JS Engine & Runtime/6. Hoisting.md",
    "Programming Hub/Languages/Javascript/0. Vanilla JS/5. Behind the Scenes/0. Topics/0. Topics.md",
    "Programming Hub/Languages/Javascript/0. Vanilla JS/5. Behind the Scenes/0. Topics",
    "Programming Hub/Languages/Javascript/0. Vanilla JS/5. Behind the Scenes/Behind canvas.canvas",
    "Programming Hub/Languages/C++/1. Fundamentals/3. Function/Scopes.md",
    "Programming Hub/Languages/Javascript/0. Vanilla JS/5. Behind the Scenes/1. JS Engine & Runtime/4. Regular vs Arrow Function.md",
    "Personal/Plans/Routine.md",
    "Personal/Plans/hello draw.md",
    "JavaScript Runtime in Browser.md",
    "().md",
    "Programming Hub/Languages/Javascript/0. Vanilla JS/5. Behind the Scenes/1. JS Engine & Runtime"
  ]
}